{
    "Bauen und Planen": [
        {
            "title": "Abbruchanzeige (§ 60 Absatz 3 NBauO)",
            "link": "/modulinhalte/formulare/12/AbbruchanzeigeNBauO.php",
            "description": "Abbruchanzeige (§ 60 Absatz 3 NBauO)"
        },
        {
            "title": "Antrag auf Bauvorbescheid (§ 73 NBauO)",
            "link": "/modulinhalte/formulare/12/Bauvoranfrage.php",
            "description": "Antrag auf Bauvorbescheid (§ 73 NBauO)"
        },
        {
            "title": "Antrag auf Erteilung einer sanierungsrechtlichen Genehmigung gemäß §§ 144 und 145 Baugesetzbuch (BauGB)",
            "link": "/modulinhalte/formulare/12/Sanierung_Antrag.php",
            "description": "Antrag auf Erteilung einer sanierungsrechtlichen Genehmigung gemäß §§ 144 und 145 Baugesetzbuch (BauGB)"
        },
        {
            "title": "Antrag auf Gewährung eines Zuschusses aus Mitteln zur Pflege des baulichen Kulturgutes",
            "link": "/modulinhalte/formulare/12/0610_003_Zuschusses_.php",
            "description": "Antrag auf Gewährung eines Zuschusses aus Mitteln zur Pflege des baulichen Kulturgutes"
        },
        {
            "title": "Antrag auf Prüfung möglicher Vorkaufsrechte",
            "link": "/modulinhalte/formulare/12/0600_01_Antrag_Pruef.php",
            "description": "Antrag auf Prüfung möglicher Vorkaufsrechte"
        },
        {
            "title": "Antrag auf Teilbaugenehmigung",
            "link": "/modulinhalte/formulare/12/Teilbaugenehmigung.php",
            "description": "Antrag auf Teilbaugenehmigung"
        },
        {
            "title": "Antrag auf Umwandlung in Wohneigentum",
            "link": "/modulinhalte/formulare/12/603_ITe007_Umwandlun.php",
            "description": "Antrag auf Umwandlung in Wohneigentum"
        },
        {
            "title": "Antrag auf Verlängerung der Geltungsdauer der Baugenehmigung, der Teilbaugenehmigung bzw. des Bauvorbescheides § 71 i.V. § 73 NBauO",
            "link": "/modulinhalte/formulare/12/603_ITeBau008.php",
            "description": "Antrag auf Verlängerung der Geltungsdauer der Baugenehmigung, der Teilbaugenehmigung bzw. des Bauvorbescheides § 71 i.V. § 73 NBauO"
        },
        {
            "title": "Antrag auf Zulassung einer Abweichung / Ausnahme / Befreiung (§ 66 NBauO)",
            "link": "/modulinhalte/formulare/12/AbweichungAusn_NbauO.php",
            "description": "Antrag auf Zulassung einer Abweichung / Ausnahme / Befreiung (§ 66 NBauO)"
        },
        {
            "title": "Antrag auf Zulassung nach § 23 Abs. 3 oder 5 BauNVO (überbaubare Grundstücksfläche)",
            "link": "/modulinhalte/formulare/12/603_009_ITeBau_Zulas.php",
            "description": "Antrag auf Zulassung nach § 23 Abs. 3 oder 5 BauNVO (überbaubare Grundstücksfläche)"
        },
        {
            "title": "Anzeige über den Beginn bestimmter Arbeiten gemäß § 76 Abs. 1 NbauO zugleich Mitteilung nach § 52 Abs. 2 und 4 NBauO",
            "link": "/modulinhalte/formulare/12/AnzeigeArbeitsbeginn.php",
            "description": "Anzeige über den Beginn bestimmter Arbeiten gemäß § 76 Abs. 1 NbauO zugleich Mitteilung nach § 52 Abs. 2 und 4 NBauO"
        },
        {
            "title": "Anzeige über die abschließende Fertigstellung des Bauvorhabens",
            "link": "/modulinhalte/formulare/12/AnzeigeFertigBauvorh.php",
            "description": "Anzeige über die abschließende Fertigstellung des Bauvorhabens"
        },
        {
            "title": "Aufnahme in das Bauwilligen Verzeichnis der Stadt Braunschweig",
            "link": "/modulinhalte/formulare/12/611_002_Bauwilligenv.php",
            "description": "Aufnahme in das Bauwilligen Verzeichnis der Stadt Braunschweig"
        },
        {
            "title": "Bauantrag gemäß § 63 bzw. § 64 der Niedersächsischen Bauordnung (NBauO)",
            "link": "/modulinhalte/formulare/12/Baugenehmig_vereinf.php",
            "description": "Bauantrag gemäß § 63 bzw. § 64 der Niedersächsischen Bauordnung (NBauO)"
        },
        {
            "title": "Bauantrag; Inhaltsverzeichnis",
            "link": "/modulinhalte/formulare/12/BauantragInhaltsverz.php",
            "description": "Bauantrag; Inhaltsverzeichnis"
        },
        {
            "title": "Bauantrag; Umgang mit wassergefährdenden Stoffen (Formular der Staatlichen Gewerbeaufsichtsämter Niedersachsen)",
            "link": "/modulinhalte/formulare/12/BauantragWassergefSt.php",
            "description": "Bauantrag; Umgang mit wassergefährdenden Stoffen (Formular der Staatlichen Gewerbeaufsichtsämter Niedersachsen)"
        },
        {
            "title": "Baudenkmal; Antrag auf denkmalrechtliche Genehmigung",
            "link": "/modulinhalte/formulare/12/Denkmal_Genehmigung.php",
            "description": "Baudenkmal; Antrag auf denkmalrechtliche Genehmigung"
        },
        {
            "title": "Bauvorlagen; Ausführungen zum Brandschutz gemäß § 11 BauVorlVO",
            "link": "/modulinhalte/formulare/12/Bauvorl_Brandschutz.php",
            "description": "Bauvorlagen; Ausführungen zum Brandschutz gemäß § 11 BauVorlVO"
        },
        {
            "title": "Beratungsstelle Planen-Bauen-Umwelt; Abgeschlossenheitsbescheinigung - Antrag",
            "link": "/modulinhalte/formulare/12/Abgeschlossen_besch.php",
            "description": "Beratungsstelle Planen-Bauen-Umwelt; Abgeschlossenheitsbescheinigung - Antrag"
        },
        {
            "title": "Beratungsstelle Planen-Bauen-Umwelt; Abgeschlossenheitsbescheinigung - Hinweise zum Antrag",
            "link": "/modulinhalte/formulare/12/Abgeschlossen_Hinw.php",
            "description": "Beratungsstelle Planen-Bauen-Umwelt; Abgeschlossenheitsbescheinigung - Hinweise zum Antrag"
        },
        {
            "title": "Beratungsstelle Planen-Bauen-Umwelt; Anfrage Bauakteneinsicht",
            "link": "/modulinhalte/formulare/12/603_006_Akteneinsich.php",
            "description": "Beratungsstelle Planen-Bauen-Umwelt; Anfrage Bauakteneinsicht"
        },
        {
            "title": "Beratungsstelle Planen-Bauen-Umwelt; Anfrage Bauberatung",
            "link": "/modulinhalte/formulare/12/603_005_Bauberatung.php",
            "description": "Beratungsstelle Planen-Bauen-Umwelt; Anfrage Bauberatung"
        },
        {
            "title": "Beratungsstelle Planen-Bauen-Umwelt; Antrag auf Auskunft aus dem Baulastenverzeichnis",
            "link": "/modulinhalte/formulare/12/Baulasten_Auskunft.php",
            "description": "Beratungsstelle Planen-Bauen-Umwelt; Antrag auf Auskunft aus dem Baulastenverzeichnis"
        },
        {
            "title": "Beratungsstelle Planen-Bauen-Umwelt; Antrag auf Entgegennahme einer Baulasterklärung",
            "link": "/modulinhalte/formulare/12/Baulasterklaerung.php",
            "description": "Beratungsstelle Planen-Bauen-Umwelt; Antrag auf Entgegennahme einer Baulasterklärung"
        },
        {
            "title": "Beratungsstelle Planen-Bauen-Umwelt; Bestellung von Auszügen aus dem Planungsrecht und / oder aus der Liegenschaftskarte",
            "link": "/modulinhalte/formulare/12/Bestellung_Planrecht.php",
            "description": "Beratungsstelle Planen-Bauen-Umwelt; Bestellung von Auszügen aus dem Planungsrecht und / oder aus der Liegenschaftskarte"
        },
        {
            "title": "Betriebsbeschreibung, Anlage zum Bauantrag",
            "link": "/modulinhalte/formulare/12/Betriebsbeschreibung.php",
            "description": "Betriebsbeschreibung, Anlage zum Bauantrag"
        },
        {
            "title": "Erklärung für die Teilnahme am digitalen Bauantragsverfahren",
            "link": "/modulinhalte/formulare/12/603_ITeBau001.php",
            "description": "Erklärung für die Teilnahme am digitalen Bauantragsverfahren"
        },
        {
            "title": "Erklärung Tragwerksplaner bei Abbruchanzeigen",
            "link": "/modulinhalte/formulare/12/Tragwerksplaner_Abbr.php",
            "description": "Erklärung Tragwerksplaner bei Abbruchanzeigen"
        },
        {
            "title": "Erklärung Tragwerksplaner bei Bauanträgen und Mitteilungen",
            "link": "/modulinhalte/formulare/12/Tragwerksplaner_Baua.php",
            "description": "Erklärung Tragwerksplaner bei Bauanträgen und Mitteilungen"
        },
        {
            "title": "Erklärung zum Verzicht auf Genehmigungsfiktion",
            "link": "/modulinhalte/formulare/12/Genehmigungsfiktion.php",
            "description": "Erklärung zum Verzicht auf Genehmigungsfiktion"
        },
        {
            "title": "Fragebogen zur Grundlagenermittlung, Ersatzneubau Okerbrücke Hüttenwerke Schrotweg",
            "link": "/modulinhalte/formulare/12/663_001_Fragebogen.php",
            "description": "Fragebogen zur Grundlagenermittlung, Ersatzneubau Okerbrücke Hüttenwerke Schrotweg"
        },
        {
            "title": "Gebäudeklasse; Angabe der Gebäudeklasse nach § 2 Abs. 3 und 5 NBauO",
            "link": "/modulinhalte/formulare/12/GebaeudeklasseNBauO.php",
            "description": "Gebäudeklasse; Angabe der Gebäudeklasse nach § 2 Abs. 3 und 5 NBauO"
        },
        {
            "title": "Geoinformationen; Bestellung von kommunalen Geodaten für Studenten und Hochschulen",
            "link": "/modulinhalte/formulare/12/612_002_Geodat_Stud.php",
            "description": "Geoinformationen; Bestellung von kommunalen Geodaten für Studenten und Hochschulen"
        },
        {
            "title": "Geoinformationen; Bestellung von kommunalen Geodaten und Stadtkarten / Themakarten",
            "link": "/modulinhalte/formulare/12/Nutzung_kom_Geodaten.php",
            "description": "Geoinformationen; Bestellung von kommunalen Geodaten und Stadtkarten / Themakarten"
        },
        {
            "title": "Grundstückszufahrten; Einverständnis der Stadt zur geplante Lage und zu ggf. baulichen Änderungen von Teilen der Straße",
            "link": "/modulinhalte/formulare/12/Grundstueckszufahrt.php",
            "description": "Grundstückszufahrten; Einverständnis der Stadt zur geplante Lage und zu ggf. baulichen Änderungen von Teilen der Straße"
        },
        {
            "title": "Mitteilung über eine genehmigungsfreie Baumaßnahme (§ 62 NBauO)",
            "link": "/modulinhalte/formulare/12/Bau_genehmigungsfrei.php",
            "description": "Mitteilung über eine genehmigungsfreie Baumaßnahme (§ 62 NBauO)"
        },
        {
            "title": "Nachweis der Berechnung der Grundflächenzahl (GRZ)/Geschossflächenzahl (GFZ) nach BauNVO 1962/1968/1977/1986",
            "link": "/modulinhalte/formulare/12/GRZ_GFZ_Nachweis_86.php",
            "description": "Nachweis der Berechnung der Grundflächenzahl (GRZ)/Geschossflächenzahl (GFZ) nach BauNVO 1962/1968/1977/1986"
        },
        {
            "title": "Nachweis der Berechnung der Grundflächenzahl (GRZ)/Geschossflächenzahl (GFZ) nach BauNVO 1990",
            "link": "/modulinhalte/formulare/12/GRZ_GFZ_Nachweis_90.php",
            "description": "Nachweis der Berechnung der Grundflächenzahl (GRZ)/Geschossflächenzahl (GFZ) nach BauNVO 1990"
        },
        {
            "title": "Steuerbescheinigung (Baudenkmal) nach §§ 7i, 10f und 11b Einkommensteuergesetz",
            "link": "/modulinhalte/formulare/12/Steuer_Baudenkmal.php",
            "description": "Steuerbescheinigung (Baudenkmal) nach §§ 7i, 10f und 11b Einkommensteuergesetz"
        },
        {
            "title": "Werbeanlagen; Hinweisblatt zum Antrag auf Bauvorbescheid / Baugenehmigung für Werbeanlagen nach NBauO",
            "link": "/modulinhalte/formulare/12/WerbeanlagenHinweise.php",
            "description": "Werbeanlagen; Hinweisblatt zum Antrag auf Bauvorbescheid / Baugenehmigung für Werbeanlagen nach NBauO"
        }
    ],
    "Einwohner-, Melde- und Personenstandswesen": [
        {
            "title": "Abmeldung ins Ausland",
            "link": "/modulinhalte/formulare/13/3241_035_Abmeldung_A.php",
            "description": "Abmeldung ins Ausland"
        },
        {
            "title": "Antrag auf Ausstellung eines Untersuchungsberechtigungsscheines (UB-Schein)",
            "link": "/modulinhalte/formulare/13/3241_029_UB-Schein.php",
            "description": "Antrag auf Ausstellung eines Untersuchungsberechtigungsscheines (UB-Schein)"
        },
        {
            "title": "Antrag auf Eintragung einer Auskunftssperre gem. § 51 Abs. 1 Bundesmeldegesetz",
            "link": "/modulinhalte/formulare/13/3241_026_Auskunftssp.php",
            "description": "Antrag auf Eintragung einer Auskunftssperre gem. § 51 Abs. 1 Bundesmeldegesetz"
        },
        {
            "title": "Eheschließung; Antrag auf Ausstellung eines Ehefähigkeitszeugnisses",
            "link": "/modulinhalte/formulare/13/Ehefaehigkeit.php",
            "description": "Eheschließung; Antrag auf Ausstellung eines Ehefähigkeitszeugnisses"
        },
        {
            "title": "Eheschließung; Vollmacht zur Anmeldung der Eheschließung",
            "link": "/modulinhalte/formulare/13/Beitrittserklaerung.php",
            "description": "Eheschließung; Vollmacht zur Anmeldung der Eheschließung"
        },
        {
            "title": "Einverständniserklärung der Eltern bei Ausweis- und Passangelegenheiten",
            "link": "/modulinhalte/formulare/13/Ausweis_einverstand.php",
            "description": "Einverständniserklärung der Eltern bei Ausweis- und Passangelegenheiten"
        },
        {
            "title": "Führungszeugnis; Antrag auf Ausstellung eines Führungszeugnisses",
            "link": "/modulinhalte/formulare/13/3241_025_Fuehrungsze.php",
            "description": "Führungszeugnis; Antrag auf Ausstellung eines Führungszeugnisses"
        },
        {
            "title": "Führungszeugnis; Antrag auf Ausstellung eines gebührenfreien Führungszeugnisses",
            "link": "/modulinhalte/formulare/13/3241_028_Gebuehrenfr.php",
            "description": "Führungszeugnis; Antrag auf Ausstellung eines gebührenfreien Führungszeugnisses"
        },
        {
            "title": "Meldewesen; Abmeldung aus Braunschweig",
            "link": "/modulinhalte/formulare/13/jue4031501003403.php",
            "description": "Meldewesen; Abmeldung aus Braunschweig"
        },
        {
            "title": "Meldewesen; Anmeldung in Braunschweig",
            "link": "/modulinhalte/formulare/13/Anmeldung_in_BS.php",
            "description": "Meldewesen; Anmeldung in Braunschweig"
        },
        {
            "title": "Meldewesen; Antrag auf eine Auskunft aus dem Melderegister gemäß § 45 Bundesmeldegesetz (erweiterte Melderegisterauskunft)",
            "link": "/modulinhalte/formulare/13/3241_031_Erweiterte_.php",
            "description": "Meldewesen; Antrag auf eine Auskunft aus dem Melderegister gemäß § 45 Bundesmeldegesetz (erweiterte Melderegisterauskunft)"
        },
        {
            "title": "Meldewesen; Einverständniserklärung der/des Sorgeberechtigten zur Anmeldung/Ummeldung",
            "link": "/modulinhalte/formulare/13/SorgeberechtEinverst.php",
            "description": "Meldewesen; Einverständniserklärung der/des Sorgeberechtigten zur Anmeldung/Ummeldung"
        },
        {
            "title": "Meldewesen; Fragebogen zur Bestimmung der Hauptwohnung",
            "link": "/modulinhalte/formulare/13/HWS_Bestimmung.php",
            "description": "Meldewesen; Fragebogen zur Bestimmung der Hauptwohnung"
        },
        {
            "title": "Meldewesen; Umzug innerhalb von Braunschweig",
            "link": "/modulinhalte/formulare/13/Umzug_in_BS.php",
            "description": "Meldewesen; Umzug innerhalb von Braunschweig"
        },
        {
            "title": "Meldewesen; Wohnungsgeberbestätigung",
            "link": "/modulinhalte/formulare/13/Wohnggeberbestaetg.php",
            "description": "Meldewesen; Wohnungsgeberbestätigung"
        },
        {
            "title": "Personenstandsregister Stadtarchiv; Bestellung von Geburts-, Heirats- und/oder Sterbeeinträgen",
            "link": "/modulinhalte/formulare/13/0414_002_BestellRegi.php",
            "description": "Personenstandsregister Stadtarchiv; Bestellung von Geburts-, Heirats- und/oder Sterbeeinträgen"
        },
        {
            "title": "Personenstandsurkunden; Bestellung Eheurkunde(n)",
            "link": "/modulinhalte/formulare/13/AnforderungEheurkund.php",
            "description": "Personenstandsurkunden; Bestellung Eheurkunde(n)"
        },
        {
            "title": "Personenstandsurkunden; Bestellung Geburtsurkunde(n)",
            "link": "/modulinhalte/formulare/13/Urkundenanforderung.php",
            "description": "Personenstandsurkunden; Bestellung Geburtsurkunde(n)"
        },
        {
            "title": "Personenstandsurkunden; Bestellung Lebenspartnerschaftsurkunde(n)",
            "link": "/modulinhalte/formulare/13/AnforderungLebenspar.php",
            "description": "Personenstandsurkunden; Bestellung Lebenspartnerschaftsurkunde(n)"
        },
        {
            "title": "Personenstandsurkunden; Bestellung Sterbeurkunde(n)",
            "link": "/modulinhalte/formulare/13/AnforderungSterbeurk.php",
            "description": "Personenstandsurkunden; Bestellung Sterbeurkunde(n)"
        },
        {
            "title": "Sterbefall; Antrag auf Aufstellung oder Änderung eines Grabmales oder einer Grabeinfassung",
            "link": "/modulinhalte/formulare/13/Sterbefall_Grabmal.php",
            "description": "Sterbefall; Antrag auf Aufstellung oder Änderung eines Grabmales oder einer Grabeinfassung"
        },
        {
            "title": "Sterbefall; Antrag auf eine Erdbestattung / Urnenbeisetzung auf dem Friedhof der Stadt Braunschweig",
            "link": "/modulinhalte/formulare/13/670_001_AntragErdUrn.php",
            "description": "Sterbefall; Antrag auf eine Erdbestattung / Urnenbeisetzung auf dem Friedhof der Stadt Braunschweig"
        },
        {
            "title": "Sterbefall; Antrag auf eine Trauerfeier / Totengedenkfeier auf dem Friedhof der Stadt Braunschweig",
            "link": "/modulinhalte/formulare/13/670_002_Trauerfeier.php",
            "description": "Sterbefall; Antrag auf eine Trauerfeier / Totengedenkfeier auf dem Friedhof der Stadt Braunschweig"
        },
        {
            "title": "Sterbefall; Antrag auf Überlassung einer Feierhalle auf einem Friedhof der Stadt Braunschweig zum Zweck einer Totengedenkfeier oder Trauerfeier",
            "link": "/modulinhalte/formulare/13/SterbefallFeierhalle.php",
            "description": "Sterbefall; Antrag auf Überlassung einer Feierhalle auf einem Friedhof der Stadt Braunschweig zum Zweck einer Totengedenkfeier oder Trauerfeier"
        },
        {
            "title": "Sterbefall; Beauftragung der Anbringung eines Sterns und einer Inschrift auf dem Stadtfriedhof/Sternenkindergrabstein",
            "link": "/modulinhalte/formulare/13/SternenkindGrabstein.php",
            "description": "Sterbefall; Beauftragung der Anbringung eines Sterns und einer Inschrift auf dem Stadtfriedhof/Sternenkindergrabstein"
        }
    ],
'Soziales und Gesundheit': [
        {'title': 'Bildung und Teilhabe, Bescheinigung für eine Klassenfahrt/einen Ausflug',
'link': '/modulinhalte/formulare/21/BuT_Bescheinigung.php',
'description': 'Bildung und Teilhabe, Bescheinigung für eine Klassenfahrt/einen Ausflug'
        },
        {'title': 'Bildung und Teilhabe, Bestätigung der Schule über die Notwendigkeit von Lernförderung Allgemein- und berufsbildende Schulen in Niedersachsen',
'link': '/modulinhalte/formulare/21/BuT_Bestaetigung.php',
'description': 'Bildung und Teilhabe, Bestätigung der Schule über die Notwendigkeit von Lernförderung Allgemein- und berufsbildende Schulen in Niedersachsen'
        },
        {'title': 'Corona-Hilfe Braunschweig',
'link': '/modulinhalte/formulare/21/000_005_Coronahilfe.php',
'description': 'Corona-Hilfe Braunschweig'
        },
        {'title': 'Eingliederungshilfe; Einreichung Berichte',
'link': '/modulinhalte/formulare/21/503_002_EinrBerichte.php',
'description': 'Eingliederungshilfe; Einreichung Berichte'
        },
        {'title': 'Inklusion; Antrag auf Gewährung einer Zuwendung für Inklusionsmaßnahmen (NBBG-Mittel)',
'link': '/modulinhalte/formulare/21/Antrag_NBGG_Mittel.php',
'description': 'Inklusion; Antrag auf Gewährung einer Zuwendung für Inklusionsmaßnahmen (NBBG-Mittel)'
        },
        {'title': 'Inklusion; Verwendungsnachweis (NBGG-Mittel)',
'link': '/modulinhalte/formulare/21/VN_NBGG_Mittel.php',
'description': 'Inklusion; Verwendungsnachweis (NBGG-Mittel)'
        },
        {'title': 'Präventionsnetzwerk gegen Kinderarmut in Braunschweig am 19. September 2024; Anmeldung',
'link': '/modulinhalte/formulare/21/0500_001_1_Fachveran.php',
'description': 'Präventionsnetzwerk gegen Kinderarmut in Braunschweig am 19. September 2024; Anmeldung'
        },
        {'title': 'Tbc: Meldeformular für Ärzte',
'link': '/modulinhalte/formulare/21/Tbc_Meldeformular.php',
'description': 'Tbc: Meldeformular für Ärzte'
        },
        {'title': 'Unterhalt; Auskunftsfragebogen zu den persönlichen und wirtschaftlichen Verhältnissen',
'link': '/modulinhalte/formulare/21/UnterhaltFragebogen.php',
'description': 'Unterhalt; Auskunftsfragebogen zu den persönlichen und wirtschaftlichen Verhältnissen'
        },
        {'title': 'Verteiler für Fachkräfte aus der Gesundheitsversorgung',
'link': '/modulinhalte/formulare/21/0500_005_Verteiler_G.php',
'description': 'Verteiler für Fachkräfte aus der Gesundheitsversorgung'
        },
        {'title': 'Verteiler für Pädagogische Fachkräfte',
'link': '/modulinhalte/formulare/21/0500_003_VerteilerPF.php',
'description': 'Verteiler für Pädagogische Fachkräfte'
        },
        {'title': 'Wohnberechtigungsschein, Antrag',
'link': '/modulinhalte/formulare/21/Wohnberechtigung.php',
'description': 'Wohnberechtigungsschein, Antrag'
        },
        {'title': 'Wohnberechtigungsschein, Einkommenserklärung der haushaltsangehörigen Personen',
'link': '/modulinhalte/formulare/21/WohnBScheinEinkommen.php',
'description': 'Wohnberechtigungsschein, Einkommenserklärung der haushaltsangehörigen Personen'
        },
        {'title': 'Wohngeld; (Anlage zum Antrag); Allgemeine Angaben eines Haushaltsmitgliedes zu seiner selbständigen Tätigkeit',
'link': '/modulinhalte/formulare/21/501_001_Angaben_Allg.php',
'description': 'Wohngeld; (Anlage zum Antrag); Allgemeine Angaben eines Haushaltsmitgliedes zu seiner selbständigen Tätigkeit'
        },
        {'title': 'Wohngeld; (Anlage zum Antrag); Angaben zu Wohnverhältnissen und zur Haushaltsführung',
'link': '/modulinhalte/formulare/21/Wohngeld_Anl_Wverh.php',
'description': 'Wohngeld; (Anlage zum Antrag); Angaben zu Wohnverhältnissen und zur Haushaltsführung'
        },
        {'title': 'Wohngeld; (Anlage zum Antrag); Angaben zum Gewinn eines Haushaltsmitgliedes mit selbständiger Tätigkeit',
'link': '/modulinhalte/formulare/21/501_002_Angaben_Gew.php',
'description': 'Wohngeld; (Anlage zum Antrag); Angaben zum Gewinn eines Haushaltsmitgliedes mit selbständiger Tätigkeit'
        },
        {'title': 'Wohngeld; (Anlage zum Antrag); Aufwendungen zur Erfüllung gesetzlicher Unterhaltsverpflichtungen',
'link': '/modulinhalte/formulare/21/Wohngeld_Anl_Unterh.php',
'description': 'Wohngeld; (Anlage zum Antrag); Aufwendungen zur Erfüllung gesetzlicher Unterhaltsverpflichtungen'
        },
        {'title': 'Wohngeld; (Anlage zum Antrag); Entgeltliche Überlassung von Wohnraum an Dritte, insbesondere bei Untervermietung',
'link': '/modulinhalte/formulare/21/Wohngeld_Anl_Ueberl.php',
'description': 'Wohngeld; (Anlage zum Antrag); Entgeltliche Überlassung von Wohnraum an Dritte, insbesondere bei Untervermietung'
        },
        {'title': 'Wohngeld; (Anlage zum Antrag); Ergänzender Fragebogen zum Wohngeldantrag für Studenten und Auszubildende',
'link': '/modulinhalte/formulare/21/Wohngeld_Anl_Ausbild.php',
'description': 'Wohngeld; (Anlage zum Antrag); Ergänzender Fragebogen zum Wohngeldantrag für Studenten und Auszubildende'
        },
        {'title': 'Wohngeld; (Anlage zum Antrag); Verdienstbescheinigung',
'link': '/modulinhalte/formulare/21/jue4036851102401.php',
'description': 'Wohngeld; (Anlage zum Antrag); Verdienstbescheinigung'
        },
        {'title': 'Wohngeld; Antrag auf Lastenzuschuss (für Eigentümer)',
'link': '/modulinhalte/formulare/21/jue4036851002406.php',
'description': 'Wohngeld; Antrag auf Lastenzuschuss (für Eigentümer)'
        },
        {'title': 'Wohngeld; Antrag auf Mietzuschuss (für Mieter).',
'link': '/modulinhalte/formulare/21/jue4036851001406.php',
'description': 'Wohngeld; Antrag auf Mietzuschuss (für Mieter).'
        },
        {'title': 'Wohngeld; Antrag auf Wohngeld - Mietzuschuss für Personen, die nicht nur vorübergehend in einem Heim wohnen',
'link': '/modulinhalte/formulare/21/WohngeldantragHeim.php',
'description': 'Wohngeld; Antrag auf Wohngeld - Mietzuschuss für Personen, die nicht nur vorübergehend in einem Heim wohnen'
        },
        {'title': 'Wohnraumhilfe; Antrag auf Einräumung von Belegungs- und Mietpreisbindungen',
'link': '/modulinhalte/formulare/21/501_003Preisbindung.php',
'description': 'Wohnraumhilfe; Antrag auf Einräumung von Belegungs- und Mietpreisbindungen'
        },
        {'title': 'Wohnraumhilfe; Antrag auf Wohnraum- und Energiesicherung',
'link': '/modulinhalte/formulare/21/501_004_Wohnraumsich.php',
'description': 'Wohnraumhilfe; Antrag auf Wohnraum- und Energiesicherung'
        },
        {'title': 'Wohnraumhilfe; Interessentenbogen Zentrale Stelle für Wohnraumhilfe',
'link': '/modulinhalte/formulare/21/Interessentenbogen.php',
'description': 'Wohnraumhilfe; Interessentenbogen Zentrale Stelle für Wohnraumhilfe'
        },
        {'title': 'Wohnraumhilfe; Wohnraumanzeige an die Zentrale Stelle für Wohnraumhilfe',
'link': '/modulinhalte/formulare/21/Wohnraumanzeige.php',
'description': 'Wohnraumhilfe; Wohnraumanzeige an die Zentrale Stelle für Wohnraumhilfe'
        }
    ]
}